<?xml version="1.0"?><bsbm>
  <querymix>
     <scalefactor>5000</scalefactor>
     <warmups>30</warmups>
     <seed>808080</seed>
     <querymixruns>150</querymixruns>
     <minquerymixruntime>0.0025</minquerymixruntime>
     <maxquerymixruntime>0.0188</maxquerymixruntime>
     <totalruntime>0.590</totalruntime>
     <qmph>915653.28</qmph>
     <cqet>0.00393</cqet>
     <cqetg>0.00376</cqetg>
  </querymix>
  <queries>
    <query nr="1">
      <executecount>0</executecount>
      <aqet>0.0</aqet>
    </query>
    <query nr="2">
      <executecount>0</executecount>
      <aqet>0.0</aqet>
    </query>
    <query nr="3">
      <executecount>0</executecount>
      <aqet>0.0</aqet>
    </query>
    <query nr="4">
      <executecount>0</executecount>
      <aqet>0.0</aqet>
    </query>
    <query nr="5">
      <executecount>0</executecount>
      <aqet>0.0</aqet>
    </query>
    <query nr="6">
      <executecount>0</executecount>
      <aqet>0.0</aqet>
    </query>
    <query nr="7">
      <executecount>0</executecount>
      <aqet>0.0</aqet>
    </query>
    <query nr="8">
      <executecount>0</executecount>
      <aqet>0.0</aqet>
    </query>
    <query nr="9">
      <executecount>0</executecount>
      <aqet>0.0</aqet>
    </query>
    <query nr="10">
      <executecount>0</executecount>
      <aqet>0.0</aqet>
    </query>
    <query nr="11">
      <executecount>0</executecount>
      <aqet>0.0</aqet>
    </query>
    <query nr="12">
      <executecount>0</executecount>
      <aqet>0.0</aqet>
    </query>
    <query nr="13">
      <executecount>0</executecount>
      <aqet>0.0</aqet>
    </query>
    <query nr="14">
      <executecount>0</executecount>
      <aqet>0.0</aqet>
    </query>
    <query nr="15">
      <executecount>0</executecount>
      <aqet>0.0</aqet>
    </query>
    <query nr="16">
      <executecount>0</executecount>
      <aqet>0.0</aqet>
    </query>
    <query nr="17">
      <executecount>0</executecount>
      <aqet>0.0</aqet>
    </query>
    <query nr="18">
      <executecount>0</executecount>
      <aqet>0.0</aqet>
    </query>
    <query nr="19">
      <executecount>0</executecount>
      <aqet>0.0</aqet>
    </query>
    <query nr="20">
      <executecount>0</executecount>
      <aqet>0.0</aqet>
    </query>
    <query nr="21">
      <executecount>0</executecount>
      <aqet>0.0</aqet>
    </query>
    <query nr="22">
      <executecount>0</executecount>
      <aqet>0.0</aqet>
    </query>
    <query nr="23">
      <executecount>0</executecount>
      <aqet>0.0</aqet>
    </query>
    <query nr="24">
      <executecount>0</executecount>
      <aqet>0.0</aqet>
    </query>
    <query nr="25">
      <executecount>0</executecount>
      <aqet>0.0</aqet>
    </query>
    <query nr="26">
      <executecount>150</executecount>
      <aqet>0.003932</aqet>
      <aqetg>0.003761</aqetg>
      <qps>254.35</qps>
      <minqet>0.00251480</minqet>
      <maxqet>0.01883010</maxqet>
      <avgresults>19.07</avgresults>
      <minresults>3</minresults>
      <maxresults>44</maxresults>
      <timeoutcount>0</timeoutcount>
    </query>
  </queries>
</bsbm>
