<?xml version="1.0"?><bsbm>
  <querymix>
     <scalefactor>5000</scalefactor>
     <warmups>30</warmups>
     <seed>808080</seed>
     <querymixruns>150</querymixruns>
     <minquerymixruntime>0.0039</minquerymixruntime>
     <maxquerymixruntime>0.0183</maxquerymixruntime>
     <totalruntime>0.961</totalruntime>
     <qmph>561791.62</qmph>
     <cqet>0.00641</cqet>
     <cqetg>0.00618</cqetg>
  </querymix>
  <queries>
    <query nr="1">
      <executecount>0</executecount>
      <aqet>0.0</aqet>
    </query>
    <query nr="2">
      <executecount>0</executecount>
      <aqet>0.0</aqet>
    </query>
    <query nr="3">
      <executecount>0</executecount>
      <aqet>0.0</aqet>
    </query>
    <query nr="4">
      <executecount>0</executecount>
      <aqet>0.0</aqet>
    </query>
    <query nr="5">
      <executecount>0</executecount>
      <aqet>0.0</aqet>
    </query>
    <query nr="6">
      <executecount>0</executecount>
      <aqet>0.0</aqet>
    </query>
    <query nr="7">
      <executecount>0</executecount>
      <aqet>0.0</aqet>
    </query>
    <query nr="8">
      <executecount>0</executecount>
      <aqet>0.0</aqet>
    </query>
    <query nr="9">
      <executecount>0</executecount>
      <aqet>0.0</aqet>
    </query>
    <query nr="10">
      <executecount>0</executecount>
      <aqet>0.0</aqet>
    </query>
    <query nr="11">
      <executecount>0</executecount>
      <aqet>0.0</aqet>
    </query>
    <query nr="12">
      <executecount>0</executecount>
      <aqet>0.0</aqet>
    </query>
    <query nr="13">
      <executecount>0</executecount>
      <aqet>0.0</aqet>
    </query>
    <query nr="14">
      <executecount>0</executecount>
      <aqet>0.0</aqet>
    </query>
    <query nr="15">
      <executecount>0</executecount>
      <aqet>0.0</aqet>
    </query>
    <query nr="16">
      <executecount>0</executecount>
      <aqet>0.0</aqet>
    </query>
    <query nr="17">
      <executecount>0</executecount>
      <aqet>0.0</aqet>
    </query>
    <query nr="18">
      <executecount>0</executecount>
      <aqet>0.0</aqet>
    </query>
    <query nr="19">
      <executecount>0</executecount>
      <aqet>0.0</aqet>
    </query>
    <query nr="20">
      <executecount>0</executecount>
      <aqet>0.0</aqet>
    </query>
    <query nr="21">
      <executecount>0</executecount>
      <aqet>0.0</aqet>
    </query>
    <query nr="22">
      <executecount>0</executecount>
      <aqet>0.0</aqet>
    </query>
    <query nr="23">
      <executecount>0</executecount>
      <aqet>0.0</aqet>
    </query>
    <query nr="24">
      <executecount>0</executecount>
      <aqet>0.0</aqet>
    </query>
    <query nr="25">
      <executecount>0</executecount>
      <aqet>0.0</aqet>
    </query>
    <query nr="26">
      <executecount>0</executecount>
      <aqet>0.0</aqet>
    </query>
    <query nr="27">
      <executecount>0</executecount>
      <aqet>0.0</aqet>
    </query>
    <query nr="28">
      <executecount>0</executecount>
      <aqet>0.0</aqet>
    </query>
    <query nr="29">
      <executecount>0</executecount>
      <aqet>0.0</aqet>
    </query>
    <query nr="30">
      <executecount>0</executecount>
      <aqet>0.0</aqet>
    </query>
    <query nr="31">
      <executecount>150</executecount>
      <aqet>0.006408</aqet>
      <aqetg>0.006184</aqetg>
      <qps>156.05</qps>
      <minqet>0.00391680</minqet>
      <maxqet>0.01825990</maxqet>
      <avgresults>9.05</avgresults>
      <minresults>0</minresults>
      <maxresults>30</maxresults>
      <timeoutcount>0</timeoutcount>
    </query>
  </queries>
</bsbm>
